<personalData>
  <ethnicGroup>0</ethnicGroup>
  <systolicBloodPressure>100</systolicBloodPressure>
  <yearOfBirth>1952</yearOfBirth>
  <chronicRenalDisease>false</chronicRenalDisease>
  <SBPTreated>false</SBPTreated>
  <active>true</active>
  <townsendGroup>0</townsendGroup>
  <atrialFibrillation>false</atrialFibrillation>
  <dateOfBirth>18/8/1952</dateOfBirth>
  <nonSmoker>true</nonSmoker>
  <age>59</age>
  <fiveaday>true</fiveaday>
  <quitSmoker>false</quitSmoker>
  <height_m>1.68</height_m>
  <weight_kg>75.52</weight_kg>
  <diabetic>false</diabetic>
  <rheumatoidArthritis>false</rheumatoidArthritis>
  <gender>male</gender>
  <hdlCholesterol_mmol_L>1.18</hdlCholesterol_mmol_L>
  <postCode/>
  <smokerGroup>0</smokerGroup>
  <moderateAlcohol>true</moderateAlcohol>
  <totalCholesterol_mmol_L>3.98</totalCholesterol_mmol_L>
  <relativeHadCVD>true</relativeHadCVD>
  <townsend>0</townsend>
</personalData>